Metadata-Version: 2.1
Name: chesscom
Version: 0.0.0
Summary: Chess.com unofficial Python API.
Home-page: https://github.com/jeffreywardman/chesscom
Author: Jeffrey Wardman
Author-email: jeffrey.wardman@yahoo.com.au
Maintainer: Jeffrey Wardman
Maintainer-email: jeffrey.wardman@yahoo.com.au
License: MIT
Download-URL: https://github.com/jeffreywardman/chesscom/archive/v_0.0.0.tar.gz
Keywords: chess,chess.com,api
Platform: UNKNOWN
